README.md
setup.cfg
setup.py
glowworm/__init__.py
glowworm/database.py
glowworm/entity.py
glowworm/exceptions.py
glowworm.egg-info/PKG-INFO
glowworm.egg-info/SOURCES.txt
glowworm.egg-info/dependency_links.txt
glowworm.egg-info/requires.txt
glowworm.egg-info/top_level.txt