Metadata-Version: 2.1
Name: glowworm
Version: 0.0.1
Summary: A super-simple Python ORM.
Home-page: https://github.com/chrisgavin/glowworm/
License: UNKNOWN
Platform: UNKNOWN
Classifier: Programming Language :: Python :: 3
Classifier: Programming Language :: Python :: 3.7
Classifier: Programming Language :: Python :: 3 :: Only
Requires-Python: >=3.7
Provides-Extra: dev
